piranha/__init__.py
piranha/__version__.py
piranha/client.py
piranha/s3.py
piranha-0.0.5.dist-info/DESCRIPTION.rst
piranha-0.0.5.dist-info/METADATA
piranha-0.0.5.dist-info/RECORD
piranha-0.0.5.dist-info/WHEEL
piranha-0.0.5.dist-info/metadata.json
piranha-0.0.5.dist-info/top_level.txt
