Metadata-Version: 2.0
Name: piranha
Version: 0.0.5
Summary: My most common boto3 use cases
Home-page: https://github.com/redvox/piranha
Author: Jens Schaa
Author-email: jens.schaa@posteo.de
License: UNKNOWN
Platform: UNKNOWN
Classifier: Development Status :: 1 - Planning
Classifier: Programming Language :: Python :: 3
Classifier: Intended Audience :: Developers
Classifier: Operating System :: OS Independent
